fasttemplate/__init__.py
fasttemplate/__version__.py
fasttemplate/assets/fastapi/default/.github/workflows/tests.yml.mako
fasttemplate/assets/fastapi/default/.gitignore.mako
fasttemplate/assets/fastapi/default/.pre-commit-config.yaml.mako
fasttemplate/assets/fastapi/default/DESCRIPTION.md
fasttemplate/assets/fastapi/default/Makefile.mako
fasttemplate/assets/fastapi/default/README.md.mako
fasttemplate/assets/fastapi/default/docker-entrypoint.sh.mako
fasttemplate/assets/fastapi/default/pyproject.toml.mako
fasttemplate/assets/fastapi/default/src/__init__.py.mako
fasttemplate/assets/fastapi/default/src/builder/__init__.py.mako
fasttemplate/assets/fastapi/default/src/builder/builder.py.mako
fasttemplate/assets/fastapi/default/src/core/__init__.py.mako
fasttemplate/assets/fastapi/default/src/core/config.py.mako
fasttemplate/assets/fastapi/default/src/main.py.mako
fasttemplate/assets/fastapi/default/src/routers/__init__.py.mako
fasttemplate/assets/fastapi/default/src/routers/root/__init__.py.mako
fasttemplate/assets/fastapi/default/src/routers/root/api.py.mako
fasttemplate/assets/fastapi/default/tests/__init__.py.mako
fasttemplate/console/__init__.py
fasttemplate/console/application.py
fasttemplate/console/commands/__init__.py
fasttemplate/console/commands/_base.py
fasttemplate/console/commands/about.py
fasttemplate/console/commands/asset.py
fasttemplate/console/commands/new.py
fasttemplate/layouts/__init__.py
fasttemplate/layouts/_base.py
fasttemplate/layouts/fastapi/__init__.py
fasttemplate/layouts/fastapi/layout.py
fasttemplate/layouts/manager.py
fasttemplate/utils/__init__.py
fasttemplate/utils/_compat.py
fasttemplate-0.0.3.dist-info/LICENSE.md
fasttemplate-0.0.3.dist-info/METADATA
fasttemplate-0.0.3.dist-info/WHEEL
fasttemplate-0.0.3.dist-info/entry_points.txt
fasttemplate-0.0.3.dist-info/RECORD
