Metadata-Version: 2.1
Name: fasttemplate
Version: 0.0.3
Summary: Python project builer
Home-page: https://github.com/koldakov/fasttemplate
Keywords: packaging,poetry,skeleton,fastapi
Author: Ivan Koldakov
Author-email: coldie322@gmail.com
Requires-Python: >=3.12,<4.0
Classifier: Programming Language :: Python :: 3
Classifier: Programming Language :: Python :: 3.12
Requires-Dist: cleo (>=2.1.0,<3.0.0)
Requires-Dist: mako (>=1.3.3,<2.0.0)
Project-URL: Repository, https://github.com/koldakov/fasttemplate
